<?xml version="1.0" encoding="UTF-8"?>
<objects serializationModel="Studio.02.02.00">
	<object class="AudioFile" id="{330fa0cd-795b-451a-8545-9457d29ac97b}">
		<property name="assetPath">
			<value>047 - Shy Guy Falls_.mp3</value>
		</property>
		<property name="isStreaming">
			<value>true</value>
		</property>
		<property name="frequencyInKHz">
			<value>32</value>
		</property>
		<property name="channelCount">
			<value>2</value>
		</property>
		<property name="length">
			<value>114.084</value>
		</property>
		<relationship name="masterAssetFolder">
			<destination>{875ee810-bc2a-472f-b6c9-bb2aee37991b}</destination>
		</relationship>
	</object>
</objects>
